LICENSE.rst
MANIFEST.in
README.rst
setup.py
jukebox_shout/__init__.py
jukebox_shout.egg-info/PKG-INFO
jukebox_shout.egg-info/SOURCES.txt
jukebox_shout.egg-info/dependency_links.txt
jukebox_shout.egg-info/requires.txt
jukebox_shout.egg-info/top_level.txt
jukebox_shout/management/__init__.py
jukebox_shout/management/commands/__init__.py
jukebox_shout/management/commands/jukebox_shout.py