Metadata-Version: 1.1
Name: jukebox-shout
Version: 0.1.1
Summary: Shoutcast streaming playback service for jukebox
Home-page: http://jensnistler.de/
Author: Jens Nistler
Author-email: opensource@jensnistler.de
License: MIT
Download-URL: http://github.com/lociii/jukebox_shout
Keywords: jukebox,music,mp3,playback,backend,shoutcast,icecast
Platform: UNKNOWN
Classifier: Programming Language :: Python
Classifier: Programming Language :: Python :: 2
Classifier: Development Status :: 3 - Alpha
Classifier: Environment :: Web Environment
Classifier: Intended Audience :: End Users/Desktop
Classifier: Intended Audience :: Developers
Classifier: License :: OSI Approved :: MIT License
Classifier: Operating System :: OS Independent
Classifier: Topic :: Multimedia :: Sound/Audio :: Players
